BugScanX/ANSI_COLORS.py
BugScanX/BugScanX.py
BugScanX/CLI.py
BugScanX/Logger.py
BugScanX/MODULES.py
BugScanX/OUTPUT.py
BugScanX/__init__.py
BugScanX/Plugin/BUG_SCAN.py
BugScanX/Plugin/CIDR_TO_IP.py
BugScanX/Plugin/HOST_TO_IP.py
BugScanX/Plugin/IP_LOOKUP.py
BugScanX/Plugin/PING.py
BugScanX/Plugin/PORT_SCAN.py
BugScanX/Plugin/RESPONSE_CHECK.py
BugScanX/Plugin/SUBFINDER.py
BugScanX/Plugin/Split_TXT.py
BugScanX/Plugin/TLS_CHECK.py
BugScanX/Plugin/__init__.py
bugscan-0.0.1.dist-info/licenses/LICENSE
bugscan-0.0.1.dist-info/METADATA
bugscan-0.0.1.dist-info/WHEEL
bugscan-0.0.1.dist-info/entry_points.txt
bugscan-0.0.1.dist-info/top_level.txt
bugscan-0.0.1.dist-info/RECORD
