Metadata-Version: 2.4
Name: BugScan
Version: 0.0.1
Summary: Bug Scanner for Internet Freedom
Author-email: RK_TECHNO_INDIA <TechnoIndian786@gmail.com>
License: MIT
Project-URL: Homepage, https://github.com/TechnoIndian/BugScanX
Project-URL: Repository, https://github.com/TechnoIndian/BugScanX.git
Project-URL: Issues, https://github.com/TechnoIndian/BugScanX/issues
Keywords: BugScanX
Classifier: License :: OSI Approved :: MIT License
Classifier: Operating System :: OS Independent
Classifier: Programming Language :: Python :: 3
Requires-Python: >=3.7
License-File: LICENSE
Requires-Dist: requests
Requires-Dist: bs4
Requires-Dist: ping3
Requires-Dist: tabulate
Dynamic: license-file
